{"otherData": {},"traceEvents":[{},{"cat":"function","dur":293061,"name":"glfwInit","ph":"X","pid":0,"tid":31992,"ts":45289672820.200},{"cat":"function","dur":418735,"name":"glfwCreateWindow","ph":"X","pid":0,"tid":31992,"ts":45289966165.800},{"cat":"function","dur":5301,"name":"void __cdecl CC3D::OpenGLContext::Init(void)","ph":"X","pid":0,"tid":31992,"ts":45290385009.900},{"cat":"function","dur":33,"name":"void __cdecl CC3D::WindowsWindow::SetVSync(bool)","ph":"X","pid":0,"tid":31992,"ts":45290390434.300},{"cat":"function","dur":718032,"name":"void __cdecl CC3D::WindowsWindow::Init(const struct CC3D::WindowProps &)","ph":"X","pid":0,"tid":31992,"ts":45289672494.200},{"cat":"function","dur":718086,"name":"__cdecl CC3D::WindowsWindow::WindowsWindow(const struct CC3D::WindowProps &)","ph":"X","pid":0,"tid":31992,"ts":45289672492.000},{"cat":"function","dur":7,"name":"void __cdecl CC3D::OpenGLRendererAPI::Init(void)","ph":"X","pid":0,"tid":31992,"ts":45290390649.400},{"cat":"function","dur":34,"name":"__cdecl CC3D::OpenGLVertexArray::OpenGLVertexArray(void)","ph":"X","pid":0,"tid":31992,"ts":45290390721.200},{"cat":"function","dur":21,"name":"__cdecl CC3D::OpenGLVertexBuffer::OpenGLVertexBuffer(float *,unsigned int)","ph":"X","pid":0,"tid":31992,"ts":45290390825.600},{"cat":"function","dur":1,"name":"void __cdecl CC3D::OpenGLVertexBuffer::Bind(void) const","ph":"X","pid":0,"tid":31992,"ts":45290391222.700},{"cat":"function","dur":376,"name":"void __cdecl CC3D::OpenGLVertexArray::AddVertexBuffer(const class std::shared_ptr<class CC3D::VertexBuffer> &)","ph":"X","pid":0,"tid":31992,"ts":45290390921.400},{"cat":"function","dur":35,"name":"__cdecl CC3D::OpenGLIndexBuffer::OpenGLIndexBuffer(unsigned int *,unsigned int)","ph":"X","pid":0,"tid":31992,"ts":45290391353.900},{"cat":"function","dur":1,"name":"void __cdecl CC3D::OpenGLIndexBuffer::Bind(void) const","ph":"X","pid":0,"tid":31992,"ts":45290391461.900},{"cat":"function","dur":59,"name":"void __cdecl CC3D::OpenGLVertexArray::SetIndexBuffer(const class std::shared_ptr<class CC3D::IndexBuffer> &)","ph":"X","pid":0,"tid":31992,"ts":45290391461.300},{"cat":"function","dur":27,"name":"__cdecl CC3D::OpenGLTexture2D::OpenGLTexture2D(unsigned int,unsigned int)","ph":"X","pid":0,"tid":31992,"ts":45290391579.000},{"cat":"function","dur":10,"name":"void __cdecl CC3D::OpenGLTexture2D::SetData(void *,unsigned int)","ph":"X","pid":0,"tid":31992,"ts":45290391667.200},{"cat":"function","dur":261,"name":"class std::basic_string<char,struct std::char_traits<char>,class std::allocator<char> > __cdecl CC3D::OpenGLShader::ReadFile(const class std::basic_string<char,struct std::char_traits<char>,class std::allocator<char> > &)","ph":"X","pid":0,"tid":31992,"ts":45290391737.300},{"cat":"function","dur":50,"name":"class std::unordered_map<unsigned int,class std::basic_string<char,struct std::char_traits<char>,class std::allocator<char> >,struct std::hash<unsigned int>,struct std::equal_to<unsigned int>,class std::allocator<struct std::pair<unsigned int const ,class std::basic_string<char,struct std::char_traits<char>,class std::allocator<char> > > > > __cdecl CC3D::OpenGLShader::PreProcess(const class std::basic_string<char,struct std::char_traits<char>,class std::allocator<char> > &)","ph":"X","pid":0,"tid":31992,"ts":45290392063.900},{"cat":"function","dur":915,"name":"void __cdecl CC3D::OpenGLShader::Compile(const class std::unordered_map<unsigned int,class std::basic_string<char,struct std::char_traits<char>,class std::allocator<char> >,struct std::hash<unsigned int>,struct std::equal_to<unsigned int>,class std::allocator<struct std::pair<unsigned int const ,class std::basic_string<char,struct std::char_traits<char>,class std::allocator<char> > > > > &)","ph":"X","pid":0,"tid":31992,"ts":45290392212.600},{"cat":"function","dur":1547,"name":"__cdecl CC3D::OpenGLShader::OpenGLShader(const class std::basic_string<char,struct std::char_traits<char>,class std::allocator<char> > &)","ph":"X","pid":0,"tid":31992,"ts":45290391735.500},{"cat":"function","dur":3,"name":"void __cdecl CC3D::OpenGLShader::Bind(void) const","ph":"X","pid":0,"tid":31992,"ts":45290393360.800},{"cat":"function","dur":98,"name":"void __cdecl CC3D::OpenGLShader::SetInt(const class std::basic_string<char,struct std::char_traits<char>,class std::allocator<char> > &,int)","ph":"X","pid":0,"tid":31992,"ts":45290393490.300},{"cat":"function","dur":2967,"name":"void __cdecl CC3D::Renderer2D::Init(void)","ph":"X","pid":0,"tid":31992,"ts":45290390709.300},{"cat":"function","dur":3113,"name":"void __cdecl CC3D::Renderer::Init(void)","ph":"X","pid":0,"tid":31992,"ts":45290390647.000},{"cat":"function","dur":1115,"name":"void __cdecl CC3D::ImGuiLayer::OnAttach(void)","ph":"X","pid":0,"tid":31992,"ts":45290393851.700},{"cat":"function","dur":1236,"name":"void __cdecl CC3D::Application::PushOverlay(class CC3D::Layer *)","ph":"X","pid":0,"tid":31992,"ts":45290393851.200},{"cat":"function","dur":722704,"name":"__cdecl CC3D::Application::Application(void)","ph":"X","pid":0,"tid":31992,"ts":45289672472.000},{"cat":"function","dur":5,"name":"__cdecl CC3D::OrthographicCamera::OrthographicCamera(float,float,float,float)","ph":"X","pid":0,"tid":31992,"ts":45290395278.900},{"cat":"function","dur":1887,"name":"stbi_load - OpenGLTexture2D::OpenGLTexture2D(const std:string&)","ph":"X","pid":0,"tid":31992,"ts":45290395411.300},{"cat":"function","dur":2101,"name":"__cdecl CC3D::OpenGLTexture2D::OpenGLTexture2D(const class std::basic_string<char,struct std::char_traits<char>,class std::allocator<char> > &)","ph":"X","pid":0,"tid":31992,"ts":45290395408.900},{"cat":"function","dur":921,"name":"stbi_load - OpenGLTexture2D::OpenGLTexture2D(const std:string&)","ph":"X","pid":0,"tid":31992,"ts":45290397625.400},{"cat":"function","dur":1070,"name":"__cdecl CC3D::OpenGLTexture2D::OpenGLTexture2D(const class std::basic_string<char,struct std::char_traits<char>,class std::allocator<char> > &)","ph":"X","pid":0,"tid":31992,"ts":45290397624.900},{"cat":"function","dur":560,"name":"stbi_load - OpenGLTexture2D::OpenGLTexture2D(const std:string&)","ph":"X","pid":0,"tid":31992,"ts":45290398796.600},{"cat":"function","dur":710,"name":"__cdecl CC3D::OpenGLTexture2D::OpenGLTexture2D(const class std::basic_string<char,struct std::char_traits<char>,class std::allocator<char> > &)","ph":"X","pid":0,"tid":31992,"ts":45290398796.200},{"cat":"function","dur":1579,"name":"stbi_load - OpenGLTexture2D::OpenGLTexture2D(const std:string&)","ph":"X","pid":0,"tid":31992,"ts":45290399611.800},{"cat":"function","dur":1712,"name":"__cdecl CC3D::OpenGLTexture2D::OpenGLTexture2D(const class std::basic_string<char,struct std::char_traits<char>,class std::allocator<char> > &)","ph":"X","pid":0,"tid":31992,"ts":45290399611.500},{"cat":"function","dur":329,"name":"stbi_load - OpenGLTexture2D::OpenGLTexture2D(const std:string&)","ph":"X","pid":0,"tid":31992,"ts":45290401421.500},{"cat":"function","dur":432,"name":"__cdecl CC3D::OpenGLTexture2D::OpenGLTexture2D(const class std::basic_string<char,struct std::char_traits<char>,class std::allocator<char> > &)","ph":"X","pid":0,"tid":31992,"ts":45290401421.100},{"cat":"function","dur":369,"name":"stbi_load - OpenGLTexture2D::OpenGLTexture2D(const std:string&)","ph":"X","pid":0,"tid":31992,"ts":45290401947.900},{"cat":"function","dur":483,"name":"__cdecl CC3D::OpenGLTexture2D::OpenGLTexture2D(const class std::basic_string<char,struct std::char_traits<char>,class std::allocator<char> > &)","ph":"X","pid":0,"tid":31992,"ts":45290401947.500},{"cat":"function","dur":378,"name":"stbi_load - OpenGLTexture2D::OpenGLTexture2D(const std:string&)","ph":"X","pid":0,"tid":31992,"ts":45290402521.800},{"cat":"function","dur":494,"name":"__cdecl CC3D::OpenGLTexture2D::OpenGLTexture2D(const class std::basic_string<char,struct std::char_traits<char>,class std::allocator<char> > &)","ph":"X","pid":0,"tid":31992,"ts":45290402521.500},{"cat":"function","dur":7726,"name":"void __cdecl CC3D::Application::PushLayer(class CC3D::Layer *)","ph":"X","pid":0,"tid":31992,"ts":45290395395.600}]}